{
    "entries": [
        {
            "rank": 1,
            "teamId": "886a70df3e144d3aae5519de82584756",
            "userName": "Muenz",
            "best_run": {
                "accuracy": 100,
                "score": 20793,
                "difficulty": 3,
                "instrument": 5,
                "stars": 6,
                "fullcombo": true
            },
            "sessions": [
                {
                    "time": 1730599664.15,
                    "valid": {
                        "accuracy": 100,
                        "score": 20793,
                        "difficulty": 3,
                        "instrument": 5,
                        "stars": 6,
                        "fullcombo": true
                    },
                    "stats": {
                        "band": {
                            "accuracy": 96,
                            "fullcombo": false,
                            "stars": 6,
                            "scores": {
                                "overdrive_bonus": 120963,
                                "base_score": 243688,
                                "total": 405609
                            }
                        },
                        "players": [
                            {
                                "accuracy": 100,
                                "score": 164686,
                                "difficulty": 3,
                                "instrument": 2,
                                "fullcombo": true,
                                "stars": 6,
                                "is_valid_entry": false
                            },
                            {
                                "accuracy": 88,
                                "score": 58208,
                                "difficulty": 2,
                                "instrument": 0,
                                "fullcombo": false,
                                "stars": 4,
                                "is_valid_entry": false
                            },
                            {
                                "accuracy": 100,
                                "score": 20793,
                                "difficulty": 3,
                                "instrument": 5,
                                "fullcombo": true,
                                "stars": 6,
                                "is_valid_entry": true
                            }
                        ]
                    }
                }
            ]
        },
        {
            "rank": 2,
            "teamId": "19711fe9074e4064a4fd6af5aceaf824",
            "userName": "Crazy_Pugy",
            "best_run": {
                "accuracy": 84,
                "score": 11679,
                "difficulty": 3,
                "instrument": 5,
                "stars": 5,
                "fullcombo": false
            },
            "sessions": [
                {
                    "time": 1730605841.172,
                    "valid": {
                        "accuracy": 84,
                        "score": 11679,
                        "difficulty": 3,
                        "instrument": 5,
                        "stars": 5,
                        "fullcombo": false
                    },
                    "stats": {
                        "band": {
                            "accuracy": 64,
                            "fullcombo": false,
                            "stars": 3,
                            "scores": {
                                "overdrive_bonus": 21044,
                                "base_score": 114905,
                                "total": 154228
                            }
                        },
                        "players": [
                            {
                                "accuracy": 14,
                                "score": 5574,
                                "difficulty": 3,
                                "instrument": 0,
                                "fullcombo": false,
                                "stars": 0,
                                "is_valid_entry": false
                            },
                            {
                                "accuracy": 84,
                                "score": 11679,
                                "difficulty": 3,
                                "instrument": 5,
                                "fullcombo": false,
                                "stars": 5,
                                "is_valid_entry": true
                            },
                            {
                                "accuracy": 95,
                                "score": 97652,
                                "difficulty": 3,
                                "instrument": 2,
                                "fullcombo": false,
                                "stars": 5,
                                "is_valid_entry": false
                            }
                        ]
                    }
                }
            ]
        },
        {
            "rank": 3,
            "teamId": "8e5ac38f550843928ae2b86efeb27b59",
            "userName": "Zz_Dylan_xX",
            "best_run": {
                "accuracy": 88,
                "score": 7854,
                "difficulty": 0,
                "instrument": 5,
                "stars": 4,
                "fullcombo": false
            },
            "sessions": [
                {
                    "time": 1730637808.203,
                    "valid": {
                        "accuracy": 88,
                        "score": 7854,
                        "difficulty": 0,
                        "instrument": 5,
                        "stars": 4,
                        "fullcombo": false
                    },
                    "stats": {
                        "band": {
                            "accuracy": 92,
                            "fullcombo": false,
                            "stars": 5,
                            "scores": {
                                "overdrive_bonus": 20371,
                                "base_score": 119093,
                                "total": 161192
                            }
                        },
                        "players": [
                            {
                                "accuracy": 88,
                                "score": 7854,
                                "difficulty": 0,
                                "instrument": 5,
                                "fullcombo": false,
                                "stars": 4,
                                "is_valid_entry": true
                            },
                            {
                                "accuracy": 84,
                                "score": 3620,
                                "difficulty": 2,
                                "instrument": 5,
                                "fullcombo": false,
                                "stars": 2,
                                "is_valid_entry": false
                            },
                            {
                                "accuracy": 97,
                                "score": 92396,
                                "difficulty": 2,
                                "instrument": 0,
                                "fullcombo": false,
                                "stars": 5,
                                "is_valid_entry": false
                            },
                            {
                                "accuracy": 100,
                                "score": 15221,
                                "difficulty": 2,
                                "instrument": 1,
                                "fullcombo": true,
                                "stars": 5,
                                "is_valid_entry": false
                            }
                        ]
                    }
                }
            ]
        },
        {
            "rank": 4,
            "teamId": "b51aabad4df04a6db423543cf97e456f",
            "userName": "Quantum_Colors",
            "best_run": {
                "accuracy": 84,
                "score": 3620,
                "difficulty": 2,
                "instrument": 5,
                "stars": 2,
                "fullcombo": false
            },
            "sessions": [
                {
                    "time": 1730637808.204,
                    "valid": {
                        "accuracy": 84,
                        "score": 3620,
                        "difficulty": 2,
                        "instrument": 5,
                        "stars": 2,
                        "fullcombo": false
                    },
                    "stats": {
                        "band": {
                            "accuracy": 92,
                            "fullcombo": false,
                            "stars": 5,
                            "scores": {
                                "overdrive_bonus": 20371,
                                "base_score": 119093,
                                "total": 161192
                            }
                        },
                        "players": [
                            {
                                "accuracy": 88,
                                "score": 7854,
                                "difficulty": 0,
                                "instrument": 5,
                                "fullcombo": false,
                                "stars": 4,
                                "is_valid_entry": false
                            },
                            {
                                "accuracy": 84,
                                "score": 3620,
                                "difficulty": 2,
                                "instrument": 5,
                                "fullcombo": false,
                                "stars": 2,
                                "is_valid_entry": true
                            },
                            {
                                "accuracy": 97,
                                "score": 92396,
                                "difficulty": 2,
                                "instrument": 0,
                                "fullcombo": false,
                                "stars": 5,
                                "is_valid_entry": false
                            },
                            {
                                "accuracy": 100,
                                "score": 15221,
                                "difficulty": 2,
                                "instrument": 1,
                                "fullcombo": true,
                                "stars": 5,
                                "is_valid_entry": false
                            }
                        ]
                    }
                }
            ]
        },
        {
            "rank": 5,
            "teamId": "542e0af77bf441e6a27538cd2b0a67aa",
            "userName": "RogueArmageddon",
            "best_run": {
                "accuracy": 65,
                "score": 2969,
                "difficulty": 1,
                "instrument": 5,
                "stars": 2,
                "fullcombo": false
            },
            "sessions": [
                {
                    "time": 1730599437.514,
                    "valid": {
                        "accuracy": 65,
                        "score": 2969,
                        "difficulty": 1,
                        "instrument": 5,
                        "stars": 2,
                        "fullcombo": false
                    },
                    "stats": {
                        "band": {
                            "accuracy": 87,
                            "fullcombo": false,
                            "stars": 4,
                            "scores": {
                                "overdrive_bonus": 55813,
                                "base_score": 165508,
                                "total": 249022
                            }
                        },
                        "players": [
                            {
                                "accuracy": 65,
                                "score": 2969,
                                "difficulty": 1,
                                "instrument": 5,
                                "fullcombo": false,
                                "stars": 2,
                                "is_valid_entry": true
                            },
                            {
                                "accuracy": 100,
                                "score": 131811,
                                "difficulty": 2,
                                "instrument": 2,
                                "fullcombo": true,
                                "stars": 5,
                                "is_valid_entry": false
                            },
                            {
                                "accuracy": 96,
                                "score": 26815,
                                "difficulty": 1,
                                "instrument": 3,
                                "fullcombo": false,
                                "stars": 4,
                                "is_valid_entry": false
                            }
                        ]
                    }
                }
            ]
        },
        {
            "rank": 6,
            "teamId": "4e31fb5700044183821898ea34920679",
            "userName": "Moocheronii",
            "best_run": {
                "accuracy": 48,
                "score": 1948,
                "difficulty": 3,
                "instrument": 5,
                "stars": 1,
                "fullcombo": false
            },
            "sessions": [
                {
                    "time": 1730611170.007,
                    "valid": {
                        "accuracy": 48,
                        "score": 1948,
                        "difficulty": 3,
                        "instrument": 5,
                        "stars": 1,
                        "fullcombo": false
                    },
                    "stats": {
                        "band": {
                            "accuracy": 70,
                            "fullcombo": false,
                            "stars": 2,
                            "scores": {
                                "overdrive_bonus": 356,
                                "base_score": 54825,
                                "total": 60300
                            }
                        },
                        "players": [
                            {
                                "accuracy": 48,
                                "score": 1948,
                                "difficulty": 3,
                                "instrument": 5,
                                "fullcombo": false,
                                "stars": 1,
                                "is_valid_entry": true
                            },
                            {
                                "accuracy": 93,
                                "score": 52876,
                                "difficulty": 3,
                                "instrument": 2,
                                "fullcombo": false,
                                "stars": 3,
                                "is_valid_entry": false
                            }
                        ]
                    }
                }
            ]
        },
        {
            "rank": 7,
            "teamId": "51454a5525714139ba11823305ff746d",
            "userName": "nowifipassword",
            "best_run": {
                "accuracy": 0,
                "score": 0,
                "difficulty": 2,
                "instrument": 5,
                "stars": 0,
                "fullcombo": false
            },
            "sessions": [
                {
                    "time": 1730581845.07,
                    "valid": {
                        "accuracy": 0,
                        "score": 0,
                        "difficulty": 2,
                        "instrument": 5,
                        "stars": 0,
                        "fullcombo": false
                    },
                    "stats": {
                        "band": {
                            "accuracy": 63,
                            "fullcombo": false,
                            "stars": 3,
                            "scores": {
                                "overdrive_bonus": 7890,
                                "base_score": 95830,
                                "total": 122169
                            }
                        },
                        "players": [
                            {
                                "accuracy": 0,
                                "score": 0,
                                "difficulty": 2,
                                "instrument": 5,
                                "fullcombo": false,
                                "stars": 0,
                                "is_valid_entry": true
                            },
                            {
                                "accuracy": 94,
                                "score": 50000,
                                "difficulty": 2,
                                "instrument": 0,
                                "fullcombo": false,
                                "stars": 3,
                                "is_valid_entry": false
                            },
                            {
                                "accuracy": 97,
                                "score": 45829,
                                "difficulty": 2,
                                "instrument": 2,
                                "fullcombo": false,
                                "stars": 3,
                                "is_valid_entry": false
                            }
                        ]
                    }
                }
            ]
        },
        {
            "rank": 8,
            "teamId": "4bb2a257c9bf4f0a912dfc243a9f80f2",
            "userName": "spongebob2942",
            "best_run": {
                "accuracy": 0,
                "score": 0,
                "difficulty": 1,
                "instrument": 5,
                "stars": 0,
                "fullcombo": false
            },
            "sessions": [
                {
                    "time": 1730588761.453,
                    "valid": {
                        "accuracy": 0,
                        "score": 0,
                        "difficulty": 1,
                        "instrument": 5,
                        "stars": 0,
                        "fullcombo": false
                    },
                    "stats": {
                        "band": {
                            "accuracy": 72,
                            "fullcombo": false,
                            "stars": 4,
                            "scores": {
                                "overdrive_bonus": 64309,
                                "base_score": 256316,
                                "total": 364593
                            }
                        },
                        "players": [
                            {
                                "accuracy": 0,
                                "score": 0,
                                "difficulty": 1,
                                "instrument": 5,
                                "fullcombo": false,
                                "stars": 0,
                                "is_valid_entry": true
                            },
                            {
                                "accuracy": 94,
                                "score": 62214,
                                "difficulty": 3,
                                "instrument": 3,
                                "fullcombo": false,
                                "stars": 4,
                                "is_valid_entry": false
                            },
                            {
                                "accuracy": 98,
                                "score": 92429,
                                "difficulty": 3,
                                "instrument": 2,
                                "fullcombo": false,
                                "stars": 5,
                                "is_valid_entry": false
                            },
                            {
                                "accuracy": 98,
                                "score": 101672,
                                "difficulty": 2,
                                "instrument": 2,
                                "fullcombo": false,
                                "stars": 5,
                                "is_valid_entry": false
                            }
                        ]
                    }
                }
            ]
        }
    ]
}